ShippingLanes.cp310-win_amd64.pyd
ShippingLanes-1.1.dist-info/METADATA
ShippingLanes-1.1.dist-info/WHEEL
ShippingLanes-1.1.dist-info/top_level.txt
ShippingLanes-1.1.dist-info/RECORD
