Metadata-Version: 2.1
Name: ShippingLanes
Version: 1.1
Summary: Python package that routes shipping lanes against US highway networks.
